cntc260/__init__.py
cntc260/demo.py
cntc260/tc260.py
cntc260-0.0.2.dist-info/licenses/LICENSE
cntc260-0.0.2.dist-info/METADATA
cntc260-0.0.2.dist-info/WHEEL
cntc260-0.0.2.dist-info/top_level.txt
cntc260-0.0.2.dist-info/RECORD
