Metadata-Version: 2.4
Name: cntc260
Version: 0.0.2
Home-page: https://github.com/OPN48/cntc260
Author: cuba3
Author-email: cuba3@163.com
License-File: LICENSE
Dynamic: author
Dynamic: author-email
Dynamic: description
Dynamic: home-page
Dynamic: license-file
